minion_mobile/__init__.py
minion_mobile/adb_client.py
minion_mobile/mobile_computer.py
minion_mobile/ui_dump_parser.py
minion_mobile-0.1.0.dist-info/licenses/LICENSE
minion_mobile-0.1.0.dist-info/METADATA
minion_mobile-0.1.0.dist-info/WHEEL
minion_mobile-0.1.0.dist-info/top_level.txt
minion_mobile-0.1.0.dist-info/RECORD
