Metadata-Version: 2.4
Name: minion-mobile
Version: 0.1.0
Summary: Python library for AI-driven mobile device automation
Home-page: https://github.com/femtozheng/minion-mobile
Author: FemtoZheng
Author-email: femtozheng@example.com
Project-URL: Bug Tracker, https://github.com/femtozheng/minion-mobile/issues
Project-URL: Documentation, https://github.com/femtozheng/minion-mobile#readme
Project-URL: Source Code, https://github.com/femtozheng/minion-mobile
Keywords: mobile,android,automation,adb,testing,ai,minion
Classifier: Programming Language :: Python :: 3
Classifier: Programming Language :: Python :: 3.8
Classifier: Programming Language :: Python :: 3.9
Classifier: Programming Language :: Python :: 3.10
Classifier: Programming Language :: Python :: 3.11
Classifier: License :: OSI Approved :: MIT License
Classifier: Operating System :: OS Independent
Classifier: Topic :: Software Development :: Libraries :: Python Modules
Classifier: Topic :: Software Development :: Testing
Classifier: Intended Audience :: Developers
Requires-Python: >=3.8
License-File: LICENSE
Requires-Dist: pydantic>=2.4.2
Requires-Dist: typing-extensions>=4.5.0
Requires-Dist: aiohttp>=3.8.0
Requires-Dist: pillow>=9.0.0
Requires-Dist: numpy>=1.20.0
Dynamic: author
Dynamic: author-email
Dynamic: classifier
Dynamic: description
Dynamic: description-content-type
Dynamic: home-page
Dynamic: keywords
Dynamic: license-file
Dynamic: project-url
Dynamic: requires-dist
Dynamic: requires-python
Dynamic: summary
